spotify_klio/__init__.py
spotify_klio/transforms/__init__.py
spotify_klio/transforms/_benchmark.py
spotify_klio/transforms/clients.py
spotify_klio/transforms/decorators.py
spotify_klio/transforms/io.py
spotify_klio-21.9.0.dev1.dist-info/METADATA
spotify_klio-21.9.0.dev1.dist-info/WHEEL
spotify_klio-21.9.0.dev1.dist-info/dependency_links.txt
spotify_klio-21.9.0.dev1.dist-info/top_level.txt
spotify_klio-21.9.0.dev1.dist-info/RECORD
